streamlit_sync/__init__.py
streamlit_sync/exceptions.py
streamlit_sync/rooms.py
streamlit_sync/st_hack.py
streamlit_sync/synced_state.py
streamlit_sync/ui.py
streamlit_sync/utils.py
streamlit_sync-0.1.0.dist-info/LICENSE
streamlit_sync-0.1.0.dist-info/WHEEL
streamlit_sync-0.1.0.dist-info/METADATA
streamlit_sync-0.1.0.dist-info/RECORD
